<?xml version="1.0" encoding="ISO-8859-1"?>
<!-- 4219595, 362nd Fighter Squandron, 357th Fighter Group, of the 
     United States Army Air Force. Hayward AFB, California.  1943. -->
<PropertyList>

  <sim>
    
    <model>
      <livery>
        <name type="string">362Sqn USAAF</name>
        <texture>Liveries/1024x1024/362FS_USAAF.png</texture>
        <specular>
          <red>   0.05 </red>
          <green> 0.05 </green>
          <blue>  0.05 </blue>
        </specular>
      </livery>
    </model>
    
  </sim>

</PropertyList>
